cythonnestednumpy/README.MD
cythonnestednumpy/__init__.py
cythonnestednumpy/requirements.txt
cythonnestednumpy/thirdparty.json
cythonnestednumpy/xxhash.c
cythonnestednumpy/xxhash.h
cythonnestednumpy-0.10.dist-info/LICENSE.rst
cythonnestednumpy-0.10.dist-info/METADATA
cythonnestednumpy-0.10.dist-info/WHEEL
cythonnestednumpy-0.10.dist-info/top_level.txt
cythonnestednumpy-0.10.dist-info/RECORD
