Metadata-Version: 2.1
Name: cythonnestednumpy
Version: 0.10
Summary: performs sorting and grouping operations on multidimensional NumPy arrays using Cython and hash-based algorithms.
Home-page: https://github.com/hansalemaos/cythonnestednumpy
Author: Johannes Fischer
Author-email: aulasparticularesdealemaosp@gmail.com
License: MIT
Keywords: cython,arrays
Classifier: Development Status :: 4 - Beta
Classifier: Programming Language :: Python :: 3 :: Only
Classifier: Programming Language :: Python :: 3.10
Classifier: Topic :: Software Development :: Libraries :: Python Modules
Classifier: Topic :: Utilities
License-File: LICENSE.rst
Requires-Dist: Cython
Requires-Dist: cythonanyarray
Requires-Dist: numpy
